0x06. Python - Classes and Objects

0. My first square
an empty class Square that defines a square:

1. Square with size
a class Square that defines a square by: (based on 0-square.py)

2. Size validation
a class Square that defines a square by: (based on 1-square.py)

3. Area of a square
a class Square that defines a square by: (based on 2-square.py)

4. Access and update private attribute
a class Square that defines a square by: (based on 3-square.py)

5. Printing a square
a class Square that defines a square by: (based on 4-square.py)

6. Coordinates of a square
a class Square that defines a square by: (based on 5-square.py)

7. Singly linked list
a class Node that defines a node of a singly linked list by:

Private instance attribute: data:
property def data(self): to retrieve it
property setter def data(self, value): to set it:
data must be an integer, otherwise raise a TypeError exception with the message data must be an integer
Private instance attribute: next_node:
property def next_node(self): to retrieve it
property setter def next_node(self, value): to set it:
next_node can be None or must be a Node, otherwise raise a TypeError exception with the message next_node must be a Node object
Instantiation with data and next_node: def __init__(self, data, next_node=None):

a class SinglyLinkedList that defines a singly linked list by:

Private instance attribute: head (no setter or getter)
Simple instantiation: def __init__(self):
Should be printable:
print the entire list in stdout
one node number by line
Public instance method: def sorted_insert(self, value): that inserts a new Node into the correct sorted position in the list (increasing order)

8. Print Square instance
a class Square that defines a square by: (based on 6-square.py)

9. Compare 2 squares
a class Square that defines a square by: (based on 4-square.py)

10. ByteCode -> Python #5
Python class MagicClass that does exactly the same as the following Python bytecode:

Disassembly of __init__:
 10           0 LOAD_CONST               1 (0)
              3 LOAD_FAST                0 (self)
              6 STORE_ATTR               0 (_MagicClass__radius)

 11           9 LOAD_GLOBAL              1 (type)
             12 LOAD_FAST                1 (radius)
             15 CALL_FUNCTION            1 (1 positional, 0 keyword pair)
             18 LOAD_GLOBAL              2 (int)
             21 COMPARE_OP               9 (is not)
             24 POP_JUMP_IF_FALSE       60
             27 LOAD_GLOBAL              1 (type)
             30 LOAD_FAST                1 (radius)
             33 CALL_FUNCTION            1 (1 positional, 0 keyword pair)
             36 LOAD_GLOBAL              3 (float)
             39 COMPARE_OP               9 (is not)
             42 POP_JUMP_IF_FALSE       60

 12          45 LOAD_GLOBAL              4 (TypeError)
             48 LOAD_CONST               2 ('radius must be a number')
             51 CALL_FUNCTION            1 (1 positional, 0 keyword pair)
             54 RAISE_VARARGS            1
             57 JUMP_FORWARD             0 (to 60)

 13     >>   60 LOAD_FAST                1 (radius)
             63 LOAD_FAST                0 (self)
             66 STORE_ATTR               0 (_MagicClass__radius)
             69 LOAD_CONST               3 (None)
             72 RETURN_VALUE

Disassembly of area:
 17           0 LOAD_FAST                0 (self)
              3 LOAD_ATTR                0 (_MagicClass__radius)
              6 LOAD_CONST               1 (2)
              9 BINARY_POWER
             10 LOAD_GLOBAL              1 (math)
             13 LOAD_ATTR                2 (pi)
             16 BINARY_MULTIPLY
             17 RETURN_VALUE

Disassembly of circumference:
 21           0 LOAD_CONST               1 (2)
              3 LOAD_GLOBAL              0 (math)
              6 LOAD_ATTR                1 (pi)
              9 BINARY_MULTIPLY
             10 LOAD_FAST                0 (self)
             13 LOAD_ATTR                2 (_MagicClass__radius)
             16 BINARY_MULTIPLY
             17 RETURN_VALUE
